optcalc/__init__.py
optcalc/optcalc.cp313-win_amd64.pyd
optcalc/optcalc.pyi
optcalc-1.0.0.dist-info/licenses/LICENSE.txt
optcalc-1.0.0.dist-info/METADATA
optcalc-1.0.0.dist-info/WHEEL
optcalc-1.0.0.dist-info/top_level.txt
optcalc-1.0.0.dist-info/RECORD
